fastapi_depends_ext/__init__.py
fastapi_depends_ext/depends.py
fastapi_depends_ext/utils.py
fastapi_depends_ext-0.2.2.dist-info/LICENSE
fastapi_depends_ext-0.2.2.dist-info/WHEEL
fastapi_depends_ext-0.2.2.dist-info/METADATA
fastapi_depends_ext-0.2.2.dist-info/RECORD
